pt_cardano_cli/__init__.py
pt_cardano_cli/__main__.py
pt_cardano_cli/cardano_cli_completer.py
pt_cardano_cli/cardano_cli_prompt.py
pt_cardano_cli/cli_lines.py
pt_cardano_cli_pooloverflow-0.0.12.data/scripts/ptccli
pt_cardano_cli_pooloverflow-0.0.12.dist-info/METADATA
pt_cardano_cli_pooloverflow-0.0.12.dist-info/WHEEL
pt_cardano_cli_pooloverflow-0.0.12.dist-info/top_level.txt
pt_cardano_cli_pooloverflow-0.0.12.dist-info/RECORD
