Metadata-Version: 2.1
Name: pt-cardano-cli-pooloverflow
Version: 0.0.12
Summary: A simple auto-complete prompt for cardano-cli
Home-page: https://github.com/pooloverflow/pt-cardano-cli
Author: pooloverflow
Author-email: 
License: UNKNOWN
Platform: UNKNOWN
Classifier: Development Status :: 2 - Pre-Alpha
Classifier: Programming Language :: Python :: 3
Classifier: Operating System :: OS Independent
Requires-Python: >=3.6
Requires-Dist: prompt-toolkit (>=3.0.5)
